laddu/__init__.py
laddu/__init__.pyi
laddu/_backend.py
laddu/_laddu.pyi
laddu/amplitudes/__init__.py
laddu/amplitudes/__init__.pyi
laddu/amplitudes/breit_wigner.py
laddu/amplitudes/breit_wigner.pyi
laddu/amplitudes/common.py
laddu/amplitudes/common.pyi
laddu/amplitudes/kmatrix.py
laddu/amplitudes/kmatrix.pyi
laddu/amplitudes/phase_space.py
laddu/amplitudes/phase_space.pyi
laddu/amplitudes/piecewise.py
laddu/amplitudes/piecewise.pyi
laddu/amplitudes/ylm.py
laddu/amplitudes/ylm.pyi
laddu/amplitudes/zlm.py
laddu/amplitudes/zlm.pyi
laddu/data.py
laddu/data.pyi
laddu/experimental.py
laddu/experimental.pyi
laddu/extensions.py
laddu/extensions.pyi
laddu/io.py
laddu/io.pyi
laddu/laddu.py
laddu/laddu.pyi
laddu/mpi.py
laddu/mpi.pyi
laddu/py.typed
laddu/utils/__init__.py
laddu/utils/__init__.pyi
laddu/utils/variables.py
laddu/utils/variables.pyi
laddu/utils/vectors.py
laddu/utils/vectors.pyi
laddu-0.14.1.dist-info/WHEEL
laddu-0.14.1.dist-info/METADATA
laddu-0.14.1.dist-info/RECORD
